[{"text":"Working with Julie Andrews is like getting hit over the head with a valentine.","cat":"valentinesday","author":"Christopher Plummer"},{"text":"I'd rather have roses on my table than diamonds on my neck.","cat":"valentinesday","author":"Emma Goldman"},{"text":"How sweet it is!","cat":"valentinesday","author":"Jackie Gleason"},{"text":"I'm a laugh tart. I make no secret of that fact.","cat":"valentinesday","author":"Hugh Grant"},{"text":"In a recent Valentine's Day posting on her fan website, Britney Spears says that - oh, who cares?","cat":"valentinesday","author":"Amy Poehler"},{"text":"A girl should be two things: classy and fabulous.","cat":"valentinesday","author":"Coco Chanel"},{"text":"I like perfume and flowers.","cat":"valentinesday","author":"Donatella Versace"},{"text":"Look, there's no metaphysics on earth like chocolates.","cat":"valentinesday","author":"Fernando Pessoa"},{"text":"It is better to have loved and lost than never to have lost at all.","cat":"valentinesday","author":"Samuel Butler"},{"text":"Sometimes I'm so sweet even I can't stand it.","cat":"valentinesday","author":"Julie Andrews"},{"text":"It's better to have loved and lost than to have to do forty pounds of laundry a week.","cat":"valentinesday","author":"Laurence J. Peter"},{"text":"Husbands are like fires - they go out when they're left unattended.","cat":"valentinesday","author":"Cher"},{"text":"Everything's coming up roses - for me.","cat":"valentinesday","author":"Ethel Merman"},{"text":"I'm like the kid in kindergarten I really do send valentines to everyone.","cat":"valentinesday","author":"Susie Bright"},{"text":"I'd kiss a frog even if there was no promise of a Prince Charming popping out of it. I love frogs.","cat":"valentinesday","author":"Cameron Diaz"},{"text":"We are each of us angels with only one wing, and we can only fly by embracing one another.","cat":"valentinesday","author":"Luciano De Crescenzo"},{"text":"Now a soft kiss - Aye, by that kiss, I vow an endless bliss.","cat":"valentinesday","author":"John Keats"},{"text":"Love is when the desire to be desired takes you so badly that you feel you could die of it.","cat":"valentinesday","author":"Henri de Toulouse-Lautrec"},{"text":"I want a man who's kind and understanding. Is that too much to ask of a millionaire?","cat":"valentinesday","author":"Zsa Zsa Gabor"},{"text":"Soul meets soul on lovers' lips.","cat":"valentinesday","author":"Percy Bysshe Shelley"},{"text":"The heart has its reasons of which reason knows nothing.","cat":"valentinesday","author":"Blaise Pascal"}]